pycacheman/__init__.py
pycacheman/exception.py
pycacheman/py.typed
pycacheman/serializable.py
pycacheman/data/schema/serializable_cache.yaml
pycacheman-0.1.1.dist-info/METADATA
pycacheman-0.1.1.dist-info/WHEEL
pycacheman-0.1.1.dist-info/top_level.txt
pycacheman-0.1.1.dist-info/RECORD
