Metadata-Version: 2.4
Name: PyCacheMan
Version: 0.1.1
Requires-Python: >=3.10
Requires-Dist: loggerman<0.2,>=0.1
Requires-Dist: mdit<0.2,>=0.1
Requires-Dist: pkgdata<0.2,>=0.1
Requires-Dist: pyserials<0.2,>=0.1
